setup.py
singapore/__init__.py
singapore.egg-info/PKG-INFO
singapore.egg-info/SOURCES.txt
singapore.egg-info/dependency_links.txt
singapore.egg-info/requires.txt
singapore.egg-info/top_level.txt