Metadata-Version: 1.0
Name: singapore
Version: 0.0.1.1
Summary: A unified Python API Wrapper for Data.gov.sg services
Home-page: https://github.com/codelah/singapore
Author: CodeSG
Author-email: zhchua@gmail.com
License: UNKNOWN
Keywords: data.gov.sg,python,wrapper,psi,nea,onemap,singapore
Platform: UNKNOWN
